cotohappy/__init__.py
cotohappy/api.py
cotohappy/error.py
cotohappy/reshape.py
cotohappy/translate.py
cotohappy-0.4.2.dist-info/METADATA
cotohappy-0.4.2.dist-info/WHEEL
cotohappy-0.4.2.dist-info/top_level.txt
cotohappy-0.4.2.dist-info/RECORD
