Metadata-Version: 2.1
Name: cotohappy
Version: 0.4.2
Summary: Cotoha API, created by NTT Communications Corporation, for Python
Home-page: https://github.com/278mt/cotohappy
Author: 278Mt
Author-email: 278mt.l.meitner@gmail.com
License: MIT
Keywords: cotohappy CotohapPy cotoha library
Platform: UNKNOWN
Classifier: License :: OSI Approved :: MIT License
Classifier: Programming Language :: Python :: 3.8
Classifier: Programming Language :: Python :: 3.7
Requires-Dist: requests
